{"stats":{"minecraft:crafted":{"minecraft:red_dye":3,"minecraft:oak_planks":20,"minecraft:crafting_table":1,"minecraft:stick":12,"minecraft:wooden_pickaxe":1,"minecraft:stone_pickaxe":1,"minecraft:stone_sword":1,"minecraft:red_bed":1,"minecraft:white_bed":2,"minecraft:cobblestone_stairs":4,"minecraft:torch":20,"minecraft:stone_axe":1},"minecraft:dropped":{"minecraft:white_wool":3},"minecraft:killed":{"minecraft:sheep":14,"minecraft:pig":2,"minecraft:cow":5},"minecraft:custom":{"minecraft:time_since_rest":1762,"minecraft:interact_with_furnace":2,"minecraft:sprint_one_cm":1291,"minecraft:damage_taken":360,"minecraft:walk_one_cm":212199,"minecraft:mob_kills":21,"minecraft:drop":1,"minecraft:damage_dealt":1945,"minecraft:interact_with_crafting_table":9,"minecraft:fly_one_cm":764,"minecraft:open_chest":1,"minecraft:crouch_one_cm":3755,"minecraft:play_time":32346,"minecraft:sneak_time":1821,"minecraft:jump":235,"minecraft:sleep_in_bed":4,"minecraft:leave_game":2,"minecraft:time_since_death":32346,"minecraft:total_world_time":32346,"minecraft:fall_one_cm":3008},"minecraft:picked_up":{"minecraft:crafting_table":1,"minecraft:leather":3,"minecraft:brown_wool":1,"minecraft:torch":1,"minecraft:porkchop":3,"minecraft:oak_log":20,"minecraft:mossy_cobblestone":1,"minecraft:dirt":44,"minecraft:wheat_seeds":1,"minecraft:beef":12,"minecraft:poppy":3,"minecraft:acacia_sapling":5,"minecraft:oak_sapling":7,"minecraft:black_wool":2,"minecraft:mutton":22,"minecraft:coal":41,"minecraft:white_wool":15,"minecraft:cobblestone":72},"minecraft:used":{"minecraft:stone_sword":56,"minecraft:cobblestone_stairs":4,"minecraft:bread":4,"minecraft:stone_pickaxe":110,"minecraft:wooden_pickaxe":4,"minecraft:stone_axe":19,"minecraft:torch":6,"minecraft:mossy_cobblestone":1,"minecraft:dirt":29,"minecraft:cobblestone":4,"minecraft:crafting_table":1,"minecraft:red_bed":1,"minecraft:oak_sapling":7,"minecraft:white_bed":1,"minecraft:acacia_sapling":5},"minecraft:mined":{"minecraft:crafting_table":1,"minecraft:short_grass":7,"minecraft:oak_log":21,"minecraft:grass_block":2,"minecraft:coal_ore":41,"minecraft:poppy":3,"minecraft:dirt":27,"minecraft:tall_grass":2,"minecraft:cobblestone":2,"minecraft:stone":70,"minecraft:oak_leaves":10,"minecraft:wall_torch":1}},"DataVersion":3953}