{"stats":{"minecraft:mined":{"minecraft:birch_log":5,"minecraft:crafting_table":1,"minecraft:short_grass":1,"minecraft:grass_block":1,"minecraft:oak_log":21,"minecraft:copper_ore":1,"minecraft:stone":34},"minecraft:picked_up":{"minecraft:birch_log":5,"minecraft:crafting_table":1,"minecraft:leather":2,"minecraft:oak_log":21,"minecraft:dirt":1,"minecraft:raw_copper":6,"minecraft:beef":6,"minecraft:oak_sapling":1,"minecraft:cobblestone":34},"minecraft:used":{"minecraft:stone_pickaxe":32,"minecraft:wooden_pickaxe":3,"minecraft:stone_axe":25,"minecraft:dirt":1,"minecraft:crafting_table":1,"minecraft:oak_sapling":1},"minecraft:dropped":{"minecraft:raw_copper":4},"minecraft:killed":{"minecraft:cow":3},"minecraft:crafted":{"minecraft:oak_planks":84,"minecraft:crafting_table":1,"minecraft:stick":52,"minecraft:wooden_pickaxe":1,"minecraft:stone_pickaxe":1,"minecraft:furnace":2,"minecraft:birch_planks":20,"minecraft:stone_axe":1},"minecraft:custom":{"minecraft:time_since_rest":5922,"minecraft:sprint_one_cm":9701,"minecraft:walk_one_cm":21182,"minecraft:mob_kills":3,"minecraft:drop":4,"minecraft:damage_dealt":300,"minecraft:swim_one_cm":733,"minecraft:interact_with_crafting_table":3,"minecraft:fly_one_cm":14068,"minecraft:crouch_one_cm":5117,"minecraft:play_time":5922,"minecraft:sneak_time":1312,"minecraft:walk_under_water_one_cm":58,"minecraft:jump":73,"minecraft:time_since_death":5922,"minecraft:walk_on_water_one_cm":247,"minecraft:total_world_time":5922,"minecraft:fall_one_cm":2208,"minecraft:horse_one_cm":1420}},"DataVersion":3953}